seq2vec/__init__.py
seq2vec/base.py
seq2vec/data_generator.py
seq2vec/hash_text.py
seq2vec/seq2seq_auto_encoder.py
seq2vec/seq2seq_char2vec.py
seq2vec/seq2seq_cnn3D.py
seq2vec/seq2seq_dssm.py
seq2vec/seq2seq_word2vec.py
seq2vec/util.py
seq2vec/model/__init__.py
seq2vec/model/seq2vec_C2R_char.py
seq2vec/model/seq2vec_C2R_word.py
seq2vec/model/seq2vec_R2R_hash.py
seq2vec/model/seq2vec_R2R_word.py
seq2vec/model/seq2vec_base.py
seq2vec/model/seq2vec_hash_text.py
seq2vec/tests/__init__.py
seq2vec/tests/test_base.py
seq2vec/tests/test_char2vec.py
seq2vec/tests/test_dictionary.py
seq2vec/tests/test_dummy.py
seq2vec/tests/test_hash_text.py
seq2vec/tests/test_seq2seq_auto_encoder.py
seq2vec/tests/test_seq2seq_char2vec.py
seq2vec/tests/test_seq2seq_cnn3D.py
seq2vec/tests/test_seq2seq_word2vec.py
seq2vec/tests/model/__init__.py
seq2vec/tests/model/test_seq2vec_C2R_char.py
seq2vec/tests/model/test_seq2vec_C2R_word.py
seq2vec/tests/model/test_seq2vec_R2R_hash.py
seq2vec/tests/model/test_seq2vec_R2R_word.py
seq2vec/tests/model/test_seq2vec_base.py
seq2vec/tests/model/test_seq2vec_hash_text.py
seq2vec/tests/transformer/__init__.py
seq2vec/tests/transformer/test_char_embedding.py
seq2vec/tests/transformer/test_hash_embedding.py
seq2vec/tests/transformer/test_transformer_base.py
seq2vec/tests/transformer/test_utils.py
seq2vec/tests/transformer/test_word_embedding.py
seq2vec/tests/transformer/test_word_embedding_conv3D.py
seq2vec/tests/util/__init__.py
seq2vec/tests/word2vec/__init__.py
seq2vec/transformer/__init__.py
seq2vec/transformer/char_embedding.py
seq2vec/transformer/hash_embedding.py
seq2vec/transformer/transformer_base.py
seq2vec/transformer/util.py
seq2vec/transformer/word_embedding.py
seq2vec/util/__init__.py
seq2vec/util/data_generator.py
seq2vec/util/util.py
seq2vec/word2vec/__init__.py
seq2vec/word2vec/base_word2vec.py
seq2vec/word2vec/char2vec.py
seq2vec/word2vec/char2vec_dictionary.py
seq2vec-0.6.0.dist-info/DESCRIPTION.rst
seq2vec-0.6.0.dist-info/METADATA
seq2vec-0.6.0.dist-info/RECORD
seq2vec-0.6.0.dist-info/WHEEL
seq2vec-0.6.0.dist-info/metadata.json
seq2vec-0.6.0.dist-info/top_level.txt
