Metadata-Version: 2.0
Name: seq2vec
Version: 0.6.0
Summary: A package to turn sequence of words into a fix-length representation vector
Home-page: UNKNOWN
Author: cph
Author-email: UNKNOWN
License: GNU 3.0
Platform: UNKNOWN
Classifier: Programming Language :: Python
Classifier: Programming Language :: Python :: 3.5
Requires-Dist: numpy
Requires-Dist: keras
Requires-Dist: yoctol-utils
Requires-Dist: gensim (==3.1.0)
Requires-Dist: h5py
Requires-Dist: yoctol-keras-layer-zoo
Requires-Dist: tensorflow
